Stylehandler/__init__.py
Stylehandler/main.py
Stylehandler-0.0.1.dist-info/LICENSE.md
Stylehandler-0.0.1.dist-info/METADATA
Stylehandler-0.0.1.dist-info/WHEEL
Stylehandler-0.0.1.dist-info/top_level.txt
Stylehandler-0.0.1.dist-info/RECORD
